pwright-9.5.0.dist-info/METADATA
pwright-9.5.0.dist-info/WHEEL
pwright/__init__.py
pwright/__version__.py
pwright/_utils.py
pwright/async_api/__init__.py
pwright/async_api/_apis.py
pwright/async_api/_briefs.py
pwright/async_api/_cms.py
pwright/async_api/_compatibilities.py
pwright/async_api/utils.py
pwright/constants.py
pwright/sync_api/__init__.py
pwright/sync_api/_apis.py
pwright/sync_api/_briefs.py
pwright/sync_api/_cms.py
pwright/sync_api/utils.py
pwright/typealiases.py
pwright-9.5.0.dist-info/RECORD
