Metadata-Version: 2.1
Name: pwright
Version: 9.5.0
Requires-Python: >=3.8
Requires-Dist: playwright>=1.34.0
